Workbook
Name NativeTimeline_Order_Date: #N/A
Name Slicer_Category: #N/A
Name Slicer_Region: #N/A

Sheet Exam_Quation
A1: Sr.No | B1: Task Description
A2: 1 | B2: Time Limit: 3 hours
A3: 2 | B3: Choose any dataset from Kaggle/UCI ML Repository
A4: 3 | B4: Create an interactive dashboard
A5: 4 | B5: Complete tasks in order listed
A6: 5 | B6: Save work every 15 minutes
A7: 6 | B7: Submit final file as 'YourName_ExcelDashboard.xlsx'
A11: Sr.No | B11: Task Description | C11: Skills Tested | D11: Time Estimate Min | E11: Weightage
A12: 1 | B12: Dataset Selection & Import | C12: Data Import, Initial Cleaning | D12: 15 | E12: 0.05
A13: 2 | B13: Data Cleaning & Preparation | C13: Remove duplicates, Handle missing values, Format data types | D13: 25 | E13: 0.1
A14: 3 | B14: Create Pivot Tables | C14: Data Analysis, Summarization | D14: 30 | E14: 0.15
A15: 4 | B15: Advanced Formulas | C15: VLOOKUP, INDEX-MATCH, IF conditions, nested functions | D15: 35 | E15: 0.15
A16: 5 | B16: Data Visualization | C16: Charts, Conditional Formatting | D16: 40 | E16: 0.2
A17: 6 | B17: Interactive Dashboard | C17: Slicers, Timeline, Dynamic ranges | D17: 45 | E17: 0.25
A18: 7 | B18: Documentation | C18: Sheet organization, Naming conventions, Instructions | D18: 20 | E18: 0.1

Sheet Sales_Data
A1: Order ID | B1: Order Date | C1: Region | D1: Category | E1: Product_Name | F1: Customer_Name | G1: Quantity | H1: Sales | I1: Discount | J1: Profit | K1: Profit Margin
A2: ORD100002 | B2: 45024 | C2: West | D2: Furniture | E2: Desk | F2: Vivaan Shah | G2: 2 | H2: 3497.31 | I2: 0.1 | J2: 621.59 | K2: 0.17773374
A3: ORD100003 | B3: 45099 | C3: East | D3: Furniture | E3: Monitor | F3: Ritika Sharma | G3: 2 | H3: 3231.61 | I3: 0.05 | J3: 854.93 | K3: 0.26455234
A4: ORD100004 | B4: 45046 | C4: North | D4: Technology | E4: Desk | F4: Mohit Agarwal | G4: 6 | H4: 3844.45 | I4: 0.1 | J4: 731.23 | K4: 0.19020406
A5: ORD100005 | B5: 45103 | C5: East | D5: Furniture | E5: Desk | F5: Mohit Agarwal | G5: 6 | H5: 124.67 | I5: 0.05 | J5: 12.8 | K5: 0.10267105
A6: ORD100006 | B6: 45640 | C6: East | D6: Technology | E6: Table | F6: Aditya Kumar | G6: 6 | H6: 3724.01 | I6: 0.2 | J6: 415.81 | K6: 0.11165652
A7: ORD100007 | B7: 45481 | C7: North | D7: Technology | E7: Desk | F7: Ananya Gupta | G7: 1 | H7: 3387.89 | I7: 0.15 | J7: 257.43 | K7: 0.075985348
A8: ORD100008 | B8: 45369 | C8: South | D8: Technology | E8: Laptop | F8: Vivaan Shah | G8: 3 | H8: 3105.86 | I8: 0 | J8: 787.91 | K8: 0.25368497
A9: ORD100009 | B9: 45311 | C9: West | D9: Office Supplies | E9: Printer | F9: Arjun Singh | G9: 5 | H9: 854.48 | I9: 0.1 | J9: 171.62 | K9: 0.2008473
A10: ORD100010 | B10: 45420 | C10: South | D10: Furniture | E10: Table | F10: Rohan Desai | G10: 6 | H10: 1473.23 | I10: 0.2 | J10: 308.72 | K10: 0.20955316
A11: ORD100011 | B11: 45520 | C11: East | D11: Technology | E11: Phone | F11: Ananya Gupta | G11: 4 | H11: 2056.86 | I11: 0.05 | J11: 413.8 | K11: 0.20118044
A12: ORD100012 | B12: 45408 | C12: West | D12: Office Supplies | E12: Desk | F12: Pooja Yadav | G12: 1 | H12: 2171.88 | I12: 0 | J12: 533.39 | K12: 0.24558907
A13: ORD100013 | B13: 45363 | C13: South | D13: Furniture | E13: Notebook | F13: Kavya Mehta | G13: 7 | H13: 2738.48 | I13: 0.2 | J13: 581.29 | K13: 0.21226739
... A301: ORD100301 | B301: 45120 | C301: North | D301: Furniture | E301: Chair | F301: Rahul Jain | G301: 9 | H301: 867.37 | I301: 0.15 | J301: 95.17 | K301: 0.10972249

Sheet Formula_sheet
A1: Product_name | B1: Producat_category | C1: VLOOKUP | D1: INDEX_MATCH | E1: Total Revenue | F1: IF | G1: Neastes IF | H1: AND+IF | J1: Color Legend
A2: Desk | B2: Furniture | C2: =VLOOKUP(A2,$A$2:$B$26,2,FALSE) -> Furniture | D2: =INDEX($B$2:$B$26,MATCH(A2,$A$2:$A$26,0)) -> Furniture | E2: 3497.31 | F2: =IF(E2>=4000,"High","Low") -> Low | G2: =IF(E2>=4000,"A",IF(E2>=2000,"B",IF(E2>=1000,"C","D"))) -> B | H2: =IF(AND(E2>=2000,E2<=4000),"Target Achieved","Below Target") -> Target Achieved | J2: Color | K2: Meaning
A3: Monitor | B3: Furniture | C3: =VLOOKUP(A3,$A$2:$B$26,2,FALSE) -> Furniture | D3: =INDEX($B$2:$B$26,MATCH(A3,$A$2:$A$26,0)) -> Furniture | E3: 3231.61 | F3: =IF(E3>=4000,"High","Low") -> Low | G3: =IF(E3>=4000,"A",IF(E3>=2000,"B",IF(E3>=1000,"C","D"))) -> B | H3: =IF(AND(E3>=2000,E3<=4000),"Target Achieved","Below Target") -> Target Achieved | J3: Light Green | K3: High Revenue / Target Achieved
A4: Desk | B4: Technology | C4: =VLOOKUP(A4,$A$2:$B$26,2,FALSE) -> Furniture | D4: =INDEX($B$2:$B$26,MATCH(A4,$A$2:$A$26,0)) -> Furniture | E4: 3844.45 | F4: =IF(E4>=4000,"High","Low") -> Low | G4: =IF(E4>=4000,"A",IF(E4>=2000,"B",IF(E4>=1000,"C","D"))) -> B | H4: =IF(AND(E4>=2000,E4<=4000),"Target Achieved","Below Target") -> Target Achieved | J4: Light Yellow | K4: Grade B
A5: Desk | B5: Furniture | C5: =VLOOKUP(A5,$A$2:$B$26,2,FALSE) -> Furniture | D5: =INDEX($B$2:$B$26,MATCH(A5,$A$2:$A$26,0)) -> Furniture | E5: 124.67 | F5: =IF(E5>=4000,"High","Low") -> Low | G5: =IF(E5>=4000,"A",IF(E5>=2000,"B",IF(E5>=1000,"C","D"))) -> D | H5: =IF(AND(E5>=2000,E5<=4000),"Target Achieved","Below Target") -> Below Target | J5: Light Blue | K5: Grade C
A6: Table | B6: Technology | C6: =VLOOKUP(A6,$A$2:$B$26,2,FALSE) -> Technology | D6: =INDEX($B$2:$B$26,MATCH(A6,$A$2:$A$26,0)) -> Technology | E6: 3724.01 | F6: =IF(E6>=4000,"High","Low") -> Low | G6: =IF(E6>=4000,"A",IF(E6>=2000,"B",IF(E6>=1000,"C","D"))) -> B | H6: =IF(AND(E6>=2000,E6<=4000),"Target Achieved","Below Target") -> Target Achieved | J6: Light Red | K6: Grade D
A7: Desk | B7: Technology | C7: =VLOOKUP(A7,$A$2:$B$26,2,FALSE) -> Furniture | D7: =INDEX($B$2:$B$26,MATCH(A7,$A$2:$A$26,0)) -> Furniture | E7: 3387.89 | F7: =IF(E7>=4000,"High","Low") -> Low | G7: =IF(E7>=4000,"A",IF(E7>=2000,"B",IF(E7>=1000,"C","D"))) -> B | H7: =IF(AND(E7>=2000,E7<=4000),"Target Achieved","Below Target") -> Target Achieved | J7: White | K7: Normal Data
A8: Laptop | B8: Technology | C8: =VLOOKUP(A8,$A$2:$B$26,2,FALSE) -> Technology | D8: =INDEX($B$2:$B$26,MATCH(A8,$A$2:$A$26,0)) -> Technology | E8: 3105.86 | F8: =IF(E8>=4000,"High","Low") -> Low | G8: =IF(E8>=4000,"A",IF(E8>=2000,"B",IF(E8>=1000,"C","D"))) -> B | H8: =IF(AND(E8>=2000,E8<=4000),"Target Achieved","Below Target") -> Target Achieved
A9: Printer | B9: Office Supplies | C9: =VLOOKUP(A9,$A$2:$B$26,2,FALSE) -> Office Supplies | D9: =INDEX($B$2:$B$26,MATCH(A9,$A$2:$A$26,0)) -> Office Supplies | E9: 854.48 | F9: =IF(E9>=4000,"High","Low") -> Low | G9: =IF(E9>=4000,"A",IF(E9>=2000,"B",IF(E9>=1000,"C","D"))) -> D | H9: =IF(AND(E9>=2000,E9<=4000),"Target Achieved","Below Target") -> Below Target
A10: Table | B10: Furniture | C10: =VLOOKUP(A10,$A$2:$B$26,2,FALSE) -> Technology | D10: =INDEX($B$2:$B$26,MATCH(A10,$A$2:$A$26,0)) -> Technology | E10: 1473.23 | F10: =IF(E10>=4000,"High","Low") -> Low | G10: =IF(E10>=4000,"A",IF(E10>=2000,"B",IF(E10>=1000,"C","D"))) -> C | H10: =IF(AND(E10>=2000,E10<=4000),"Target Achieved","Below Target") -> Below Target
A11: Phone | B11: Technology | C11: =VLOOKUP(A11,$A$2:$B$26,2,FALSE) -> Technology | D11: =INDEX($B$2:$B$26,MATCH(A11,$A$2:$A$26,0)) -> Technology | E11: 2056.86 | F11: =IF(E11>=4000,"High","Low") -> Low | G11: =IF(E11>=4000,"A",IF(E11>=2000,"B",IF(E11>=1000,"C","D"))) -> B | H11: =IF(AND(E11>=2000,E11<=4000),"Target Achieved","Below Target") -> Target Achieved
A12: Desk | B12: Office Supplies | C12: =VLOOKUP(A12,$A$2:$B$26,2,FALSE) -> Furniture | D12: =INDEX($B$2:$B$26,MATCH(A12,$A$2:$A$26,0)) -> Furniture | E12: 2171.88 | F12: =IF(E12>=4000,"High","Low") -> Low | G12: =IF(E12>=4000,"A",IF(E12>=2000,"B",IF(E12>=1000,"C","D"))) -> B | H12: =IF(AND(E12>=2000,E12<=4000),"Target Achieved","Below Target") -> Target Achieved
A13: Notebook | B13: Furniture | C13: =VLOOKUP(A13,$A$2:$B$26,2,FALSE) -> Furniture | D13: =INDEX($B$2:$B$26,MATCH(A13,$A$2:$A$26,0)) -> Furniture | E13: 2738.48 | F13: =IF(E13>=4000,"High","Low") -> Low | G13: =IF(E13>=4000,"A",IF(E13>=2000,"B",IF(E13>=1000,"C","D"))) -> B | H13: =IF(AND(E13>=2000,E13<=4000),"Target Achieved","Below Target") -> Target Achieved
A14: Chair | B14: Technology | C14: =VLOOKUP(A14,$A$2:$B$26,2,FALSE) -> Technology | D14: =INDEX($B$2:$B$26,MATCH(A14,$A$2:$A$26,0)) -> Technology | E14: 1462.49 | F14: =IF(E14>=4000,"High","Low") -> Low | G14: =IF(E14>=4000,"A",IF(E14>=2000,"B",IF(E14>=1000,"C","D"))) -> C | H14: =IF(AND(E14>=2000,E14<=4000),"Target Achieved","Below Target") -> Below Target
A15: Printer | B15: Technology | C15: =VLOOKUP(A15,$A$2:$B$26,2,FALSE) -> Office Supplies | D15: =INDEX($B$2:$B$26,MATCH(A15,$A$2:$A$26,0)) -> Office Supplies | E15: 4716.99 | F15: =IF(E15>=4000,"High","Low") -> High | G15: =IF(E15>=4000,"A",IF(E15>=2000,"B",IF(E15>=1000,"C","D"))) -> A | H15: =IF(AND(E15>=2000,E15<=4000),"Target Achieved","Below Target") -> Below Target
A16: Laptop | B16: Furniture | C16: =VLOOKUP(A16,$A$2:$B$26,2,FALSE) -> Technology | D16: =INDEX($B$2:$B$26,MATCH(A16,$A$2:$A$26,0)) -> Technology | E16: 2740.53 | F16: =IF(E16>=4000,"High","Low") -> Low | G16: =IF(E16>=4000,"A",IF(E16>=2000,"B",IF(E16>=1000,"C","D"))) -> B | H16: =IF(AND(E16>=2000,E16<=4000),"Target Achieved","Below Target") -> Target Achieved
A17: Phone | B17: Furniture | C17: =VLOOKUP(A17,$A$2:$B$26,2,FALSE) -> Technology | D17: =INDEX($B$2:$B$26,MATCH(A17,$A$2:$A$26,0)) -> Technology | E17: 4424.41 | F17: =IF(E17>=4000,"High","Low") -> High | G17: =IF(E17>=4000,"A",IF(E17>=2000,"B",IF(E17>=1000,"C","D"))) -> A | H17: =IF(AND(E17>=2000,E17<=4000),"Target Achieved","Below Target") -> Below Target
A18: Desk | B18: Technology | C18: =VLOOKUP(A18,$A$2:$B$26,2,FALSE) -> Furniture | D18: =INDEX($B$2:$B$26,MATCH(A18,$A$2:$A$26,0)) -> Furniture | E18: 3618.24 | F18: =IF(E18>=4000,"High","Low") -> Low | G18: =IF(E18>=4000,"A",IF(E18>=2000,"B",IF(E18>=1000,"C","D"))) -> B | H18: =IF(AND(E18>=2000,E18<=4000),"Target Achieved","Below Target") -> Target Achieved
A19: Phone | B19: Technology | C19: =VLOOKUP(A19,$A$2:$B$26,2,FALSE) -> Technology | D19: =INDEX($B$2:$B$26,MATCH(A19,$A$2:$A$26,0)) -> Technology | E19: 1860.74 | F19: =IF(E19>=4000,"High","Low") -> Low | G19: =IF(E19>=4000,"A",IF(E19>=2000,"B",IF(E19>=1000,"C","D"))) -> C | H19: =IF(AND(E19>=2000,E19<=4000),"Target Achieved","Below Target") -> Below Target
... A31: Laptop | B31: Office Supplies | C31: =VLOOKUP(A31,$A$2:$B$26,2,FALSE) -> Technology | D31: =INDEX($B$2:$B$26,MATCH(A31,$A$2:$A$26,0)) -> Technology | E31: 1791.85 | F31: =IF(E31>=4000,"High","Low") -> Low | G31: =IF(E31>=4000,"A",IF(E31>=2000,"B",IF(E31>=1000,"C","D"))) -> C | H31: =IF(AND(E31>=2000,E31<=4000),"Target Achieved","Below Target") -> Below Target

Sheet Pivot_table
A1: Region | B1: Sum of Sales
A2: South | B2: 210435.96
A3: North | B3: 207483.74
A4: East | B4: 193876.82
A5: West | B5: 182504.74
A6: Grand Total | B6: 794301.26
A13: Category | B13: Sum of Sales
A14: Technology | B14: 276539.29
A15: Furniture | B15: 267131.34
A16: Office Supplies | B16: 250630.63
A17: Grand Total | B17: 794301.26
A22: Product_Name | B22: Sum of Quantity
A23: Notebook | B23: 285
A24: Laptop | B24: 236
A25: Desk | B25: 206
A26: Table | B26: 204
A27: Monitor | B27: 202
A28: Chair | B28: 201
A29: Phone | B29: 185
A30: Printer | B30: 130
A31: Grand Total | B31: 1649
A37: Customer_Name | B37: Sum of Profit
A38: Aditya Kumar | B38: 12480.53
A39: Nisha Roy | B39: 10333.35
A40: Mohit Agarwal | B40: 10256.91
A41: Kavya Mehta | B41: 9387.53
A42: Diya Sharma | B42: 9140.2
A43: Rohan Desai | B43: 8560.53
A44: Arjun Singh | B44: 7888.08
A45: Vivaan Shah | B45: 7204.93
A46: Priya Patel | B46: 6857.78
A47: Sanjay Patel | B47: 6472.71
A48: Grand Total | B48: 88582.55

Sheet Instructions
A1: Sales Dashboard - Excel Practical Exam
A3: Student: Mukesh Kote | File: MukeshKote_ExcelDashboard.xlsx
A4: Sheet Name
A5: Purpose
A6: Sales_Data
A7: Raw dataset-300 Orders
A8: Pivot_table
A9: Data Analysis -4 Pivot Tables
A10: Formula_Sheet
A11: VLOOKUP, INDEX-MATCH, IF formulas
A12: Dashboard
A13: Interactive charts with Slicers
... A23: Click X button on slicer to clear the filter

Sheet Dashboard
A1: NovaMart Solutions Pvt. Ltd.
D9: Total Sales | I9: Total Profit | N9: Total Quantity | S9: Avg Discount | X9: Best Region
D11: ="₹ "&TEXT(GETPIVOTDATA("Sales",Pivot_table!$A$13)/100000,"0.00")&" L" -> ₹ 7.94 L | I11: ="₹ "&TEXT(SUM(Sales_Data!J:J)/100000,"0.00")&" L" -> ₹ 1.33 L | N11: =SUM(Sales_Data!G:G) -> 1649 | S11: =AVERAGE(Sales_Data!I:I) -> 0.0945 | X11: =Pivot_table!A2 -> South
AC66: Key Insights
AC69: Technology best category (35%)
AC72: South region leads in sales
AC75: Notebook is top selling product
AC78: Avg profit margin: 16.66%
AC81: Notebook is best selling product
AC84: Printer has lowest sales
